DiNetxify/__init__.py
DiNetxify/analysis.py
DiNetxify/analysis_pipeline.py
DiNetxify/binomial.py
DiNetxify/com_strength.py
DiNetxify/conditional_logistic.py
DiNetxify/cox.py
DiNetxify/data_management.py
DiNetxify/unconditional_logistic.py
DiNetxify/utility.py
DiNetxify/utility_data_parallel.py
DiNetxify/utility_summary.py
DiNetxify/visualization.py
DiNetxify/data/phecode_1.2/ICD-10-CM.npy
DiNetxify/data/phecode_1.2/ICD-10-WHO.npy
DiNetxify/data/phecode_1.2/ICD-9-WHO.npy
DiNetxify/data/phecode_1.2/level1_info.npy
DiNetxify/data/phecode_1.2/level2_info.npy
DiNetxify/data/phecode_1.3a/ICD-10-WHO.npy
DiNetxify/data/phecode_1.3a/ICD-9-WHO.npy
DiNetxify/data/phecode_1.3a/level1_info.npy
DiNetxify/data/phecode_1.3a/level2_info.npy
DiNetxify/data/phecode_VL_autism/ICD-10-WHO.npy
DiNetxify/data/phecode_VL_autism/ICD-9-WHO.npy
DiNetxify/data/phecode_VL_autism/level1_info.npy
DiNetxify/data/phecode_VL_autism/level2_info.npy
DiNetxify/data/phecode_VL_autism/phecode_process.py
dinetxify-0.1.10.dist-info/licenses/LICENSE
dinetxify-0.1.10.dist-info/METADATA
dinetxify-0.1.10.dist-info/WHEEL
dinetxify-0.1.10.dist-info/top_level.txt
dinetxify-0.1.10.dist-info/RECORD
