Metadata-Version: 2.4
Name: DiNetxify
Version: 0.1.10
Summary: DiNetxify
Author-email: Can Hou <houcan@wchscu.cn>, Haowen Liu <haowenliu81@gmail.com>
License:                     GNU GENERAL PUBLIC LICENSE
Project-URL: Homepage, https://github.com/HZcohort/DiNetxify/tree/package
Project-URL: Issues, https://github.com/HZcohort/DiNetxify/issues
Classifier: Programming Language :: Python :: 3
Classifier: Operating System :: OS Independent
Requires-Python: >=3.10
License-File: LICENSE
Requires-Dist: python_louvain>=0.15
Requires-Dist: matplotlib>=3.5.0
Requires-Dist: lifelines>=0.27.0
Requires-Dist: statsmodels>=0.14.4
Requires-Dist: networkx>=3.4.2
Requires-Dist: numpy>=1.21.5
Requires-Dist: pandas>=1.3.5
Requires-Dist: plotly>=5.4.0
Requires-Dist: scikit_learn>=1.0.2
Requires-Dist: scipy>=1.7.2
Requires-Dist: tqdm>=4.62.3
Dynamic: license-file
